oblivious/__init__.py
oblivious/damgardjurik.py
oblivious/distance.py
oblivious/number.py
oblivious/paillier.py
oblivious/sharing.py
obliviouspy_hss-1.1.1.dist-info/METADATA
obliviouspy_hss-1.1.1.dist-info/WHEEL
obliviouspy_hss-1.1.1.dist-info/top_level.txt
obliviouspy_hss-1.1.1.dist-info/RECORD
