Metadata-Version: 2.4
Name: obliviouspy-HSS
Version: 1.1.1
Summary: A Python library implementing the Homomorphic Secret Sharing, applied for Oblivious Linear Evaluation (OLE), Vector-OLE and NxOLE
Author: Davide Cerutti
Project-URL: Paper, https://eprint.iacr.org/2026/104
Project-URL: Homepage, https://github.com/davidecerutti/ObliviousPy
Project-URL: Bug Tracker, https://github.com/davidecerutti/ObliviousPy/issues
Classifier: Programming Language :: Python :: 3
Classifier: License :: OSI Approved :: MIT License
Classifier: Operating System :: OS Independent
Requires-Python: >=3.8
Requires-Dist: numpy>=1.21.0
